arraykit/__init__.py
arraykit/__init__.pyi
arraykit/_arraykit.c
arraykit/_arraykit.cpython-311-x86_64-linux-gnu.so
arraykit/array_go.c
arraykit/array_go.h
arraykit/array_to_tuple.c
arraykit/array_to_tuple.h
arraykit/auto_map.c
arraykit/auto_map.h
arraykit/block_index.c
arraykit/block_index.h
arraykit/delimited_to_arrays.c
arraykit/delimited_to_arrays.h
arraykit/methods.c
arraykit/methods.h
arraykit/py.typed
arraykit/tri_map.c
arraykit/tri_map.h
arraykit/utilities.h
arraykit-1.2.0.dist-info/METADATA
arraykit-1.2.0.dist-info/WHEEL
arraykit-1.2.0.dist-info/top_level.txt
arraykit-1.2.0.dist-info/RECORD
arraykit-1.2.0.dist-info/licenses/LICENSE.txt
