Metadata-Version: 2.4
Name: arraykit
Version: 1.2.0
Summary: Array utilities for StaticFrame
Author: Christopher Ariza, Brandt Bucher, Charles Burkland
License-Expression: MIT
Project-URL: Homepage, https://github.com/static-frame/arraykit
Keywords: numpy,array
Classifier: Development Status :: 5 - Production/Stable
Classifier: Intended Audience :: Developers
Classifier: Topic :: Software Development
Classifier: Programming Language :: C
Classifier: Programming Language :: Python :: Implementation :: CPython
Classifier: Operating System :: MacOS :: MacOS X
Classifier: Operating System :: Microsoft :: Windows
Classifier: Operating System :: POSIX
Classifier: Programming Language :: Python :: 3.10
Classifier: Programming Language :: Python :: 3.11
Classifier: Programming Language :: Python :: 3.12
Classifier: Programming Language :: Python :: 3.13
Classifier: Programming Language :: Python :: 3.14
Classifier: Programming Language :: Python :: Free Threading
Classifier: Typing :: Typed
Requires-Python: >=3.10
License-File: LICENSE.txt
Requires-Dist: numpy>=1.24.3
Dynamic: license-file
